qadence2_ir/__init__.py
qadence2_ir/factory.py
qadence2_ir/factory_tools.py
qadence2_ir/irast.py
qadence2_ir/irbuilder.py
qadence2_ir/types.py
qadence2_ir-0.2.0.dist-info/METADATA
qadence2_ir-0.2.0.dist-info/WHEEL
qadence2_ir-0.2.0.dist-info/RECORD
